kindle_to_md.py
kindle_to_md-1.0.0.dist-info/LICENSE
kindle_to_md-1.0.0.dist-info/METADATA
kindle_to_md-1.0.0.dist-info/WHEEL
kindle_to_md-1.0.0.dist-info/entry_points.txt
kindle_to_md-1.0.0.dist-info/top_level.txt
kindle_to_md-1.0.0.dist-info/RECORD
