Metadata-Version: 2.1
Name: kindle-to-md
Version: 1.0.0
Summary: Convert Kindle notes to MarkDown
Home-page: https://github.com/mikethicke/kindletomd
Author: Mike Thicke
Author-email: mikethicke@gmail.com
License: MIT
Keywords: kindle,markdown
Platform: UNKNOWN
Classifier: Programming Language :: Python :: 3.10
Classifier: Development Status :: 5 - Production/Stable
Classifier: License :: OSI Approved :: MIT License
Classifier: Operating System :: OS Independent
Classifier: Topic :: Text Processing :: Markup :: Markdown
Classifier: Topic :: Utilities
Requires-Python: >=3.10
License-File: LICENSE
